__init__.py
jeremydimond_pymlga-0.6.7.dist-info/licenses/LICENSE
pymlga/__init__.py
pymlga/allele.py
pymlga/chromosome.py
pymlga/evaluation.py
pymlga/experiment.py
pymlga/gene.py
pymlga/generation.py
pymlga/individual.py
pymlga/reproduction.py
jeremydimond_pymlga-0.6.7.dist-info/METADATA
jeremydimond_pymlga-0.6.7.dist-info/WHEEL
jeremydimond_pymlga-0.6.7.dist-info/top_level.txt
jeremydimond_pymlga-0.6.7.dist-info/RECORD
